felsen_analysis/.ipynb_checkpoints/Untitled-checkpoint.ipynb
felsen_analysis/.ipynb_checkpoints/testpackage-checkpoint.ipynb
felsen_analysis/Untitled.ipynb
felsen_analysis/__init__.py
felsen_analysis/backend/ephys.py
felsen_analysis/backend/ephysinterface.py
felsen_analysis/backend/helper.py
felsen_analysis/testpackage.ipynb
felsen_analysis/toolkit/opto.py
felsen_analysis/toolkit/plots.py
felsen_analysis/toolkit/populations.py
felsen_analysis/toolkit/prediction.py
felsen_analysis/toolkit/process.py
felsen_analysis/toolkit/saccades.py
felsen_analysis-0.1.16.dist-info/METADATA
felsen_analysis-0.1.16.dist-info/WHEEL
felsen_analysis-0.1.16.dist-info/RECORD
