Metadata-Version: 2.3
Name: felsen-analysis
Version: 0.1.16
Summary: 
Author: annabuteau
Author-email: anna.buteau@cuanschutz.edu
Requires-Python: >=3.9
Classifier: Programming Language :: Python :: 3
Classifier: Programming Language :: Python :: 3.9
Classifier: Programming Language :: Python :: 3.10
Classifier: Programming Language :: Python :: 3.11
Classifier: Programming Language :: Python :: 3.12
Classifier: Programming Language :: Python :: 3.13
Requires-Dist: requests (>=2.32.4,<3.0.0)
